{
  "results": {
    "alpha_vantage:GENERATED:2026-07-14": {
      "adjusted_close": null,
      "asset_role": "challenger",
      "carried_forward": false,
      "confidence": "low",
      "currency": null,
      "error": "No time series returned",
      "field_used": null,
      "is_final_eod_bar": null,
      "metadata": {},
      "price": null,
      "pricing_tier": "valuation_grade",
      "provider_exchange": null,
      "provider_symbol": "GENERATED",
      "provider_timestamp": null,
      "provider_timezone": null,
      "raw_close": null,
      "requested_close_date": "2026-07-14",
      "returned_close_date": null,
      "selected_close": null,
      "selected_close_type": null,
      "source": "alpha_vantage",
      "source_detail": null,
      "status": "unresolved",
      "symbol": "GENERATED",
      "verification": {
        "source": null,
        "status": "not_checked"
      }
    },
    "alpha_vantage:INTENT:2026-07-14": {
      "adjusted_close": null,
      "asset_role": "challenger",
      "carried_forward": false,
      "confidence": "low",
      "currency": null,
      "error": "No time series returned",
      "field_used": null,
      "is_final_eod_bar": null,
      "metadata": {},
      "price": null,
      "pricing_tier": "valuation_grade",
      "provider_exchange": null,
      "provider_symbol": "INTENT",
      "provider_timestamp": null,
      "provider_timezone": null,
      "raw_close": null,
      "requested_close_date": "2026-07-14",
      "returned_close_date": null,
      "selected_close": null,
      "selected_close_type": null,
      "source": "alpha_vantage",
      "source_detail": null,
      "status": "unresolved",
      "symbol": "INTENT",
      "verification": {
        "source": null,
        "status": "not_checked"
      }
    },
    "alpha_vantage:PROPOSED:2026-07-14": {
      "adjusted_close": null,
      "asset_role": "challenger",
      "carried_forward": false,
      "confidence": "low",
      "currency": null,
      "error": "No time series returned",
      "field_used": null,
      "is_final_eod_bar": null,
      "metadata": {},
      "price": null,
      "pricing_tier": "valuation_grade",
      "provider_exchange": null,
      "provider_symbol": "PROPOSED",
      "provider_timestamp": null,
      "provider_timezone": null,
      "raw_close": null,
      "requested_close_date": "2026-07-14",
      "returned_close_date": null,
      "selected_close": null,
      "selected_close_type": null,
      "source": "alpha_vantage",
      "source_detail": null,
      "status": "unresolved",
      "symbol": "PROPOSED",
      "verification": {
        "source": null,
        "status": "not_checked"
      }
    },
    "alpha_vantage:ROTATION:2026-07-14": {
      "adjusted_close": null,
      "asset_role": "challenger",
      "carried_forward": false,
      "confidence": "low",
      "currency": null,
      "error": "No time series returned",
      "field_used": null,
      "is_final_eod_bar": null,
      "metadata": {},
      "price": null,
      "pricing_tier": "valuation_grade",
      "provider_exchange": null,
      "provider_symbol": "ROTATION",
      "provider_timestamp": null,
      "provider_timezone": null,
      "raw_close": null,
      "requested_close_date": "2026-07-14",
      "returned_close_date": null,
      "selected_close": null,
      "selected_close_type": null,
      "source": "alpha_vantage",
      "source_detail": null,
      "status": "unresolved",
      "symbol": "ROTATION",
      "verification": {
        "source": null,
        "status": "not_checked"
      }
    },
    "alpha_vantage:TRADE:2026-07-14": {
      "adjusted_close": null,
      "asset_role": "challenger",
      "carried_forward": false,
      "confidence": "low",
      "currency": null,
      "error": "No time series returned",
      "field_used": null,
      "is_final_eod_bar": null,
      "metadata": {},
      "price": null,
      "pricing_tier": "valuation_grade",
      "provider_exchange": null,
      "provider_symbol": "TRADE",
      "provider_timestamp": null,
      "provider_timezone": null,
      "raw_close": null,
      "requested_close_date": "2026-07-14",
      "returned_close_date": null,
      "selected_close": null,
      "selected_close_type": null,
      "source": "alpha_vantage",
      "source_detail": null,
      "status": "unresolved",
      "symbol": "TRADE",
      "verification": {
        "source": null,
        "status": "not_checked"
      }
    },
    "alpha_vantage:WAS:2026-07-14": {
      "adjusted_close": null,
      "asset_role": "challenger",
      "carried_forward": false,
      "confidence": "low",
      "currency": null,
      "error": "No time series returned",
      "field_used": null,
      "is_final_eod_bar": null,
      "metadata": {},
      "price": null,
      "pricing_tier": "valuation_grade",
      "provider_exchange": null,
      "provider_symbol": "WAS",
      "provider_timestamp": null,
      "provider_timezone": null,
      "raw_close": null,
      "requested_close_date": "2026-07-14",
      "returned_close_date": null,
      "selected_close": null,
      "selected_close_type": null,
      "source": "alpha_vantage",
      "source_detail": null,
      "status": "unresolved",
      "symbol": "WAS",
      "verification": {
        "source": null,
        "status": "not_checked"
      }
    },
    "fmp:GENERATED:2026-07-14": {
      "adjusted_close": null,
      "asset_role": "challenger",
      "carried_forward": false,
      "confidence": "low",
      "currency": null,
      "error": "No matching EOD result",
      "field_used": null,
      "is_final_eod_bar": null,
      "metadata": {},
      "price": null,
      "pricing_tier": "valuation_grade",
      "provider_exchange": null,
      "provider_symbol": "GENERATED",
      "provider_timestamp": null,
      "provider_timezone": null,
      "raw_close": null,
      "requested_close_date": "2026-07-14",
      "returned_close_date": null,
      "selected_close": null,
      "selected_close_type": null,
      "source": "fmp",
      "source_detail": null,
      "status": "unresolved",
      "symbol": "GENERATED",
      "verification": {
        "source": null,
        "status": "not_checked"
      }
    },
    "fmp:INTENT:2026-07-14": {
      "adjusted_close": null,
      "asset_role": "challenger",
      "carried_forward": false,
      "confidence": "low",
      "currency": null,
      "error": "No matching EOD result",
      "field_used": null,
      "is_final_eod_bar": null,
      "metadata": {},
      "price": null,
      "pricing_tier": "valuation_grade",
      "provider_exchange": null,
      "provider_symbol": "INTENT",
      "provider_timestamp": null,
      "provider_timezone": null,
      "raw_close": null,
      "requested_close_date": "2026-07-14",
      "returned_close_date": null,
      "selected_close": null,
      "selected_close_type": null,
      "source": "fmp",
      "source_detail": null,
      "status": "unresolved",
      "symbol": "INTENT",
      "verification": {
        "source": null,
        "status": "not_checked"
      }
    },
    "fmp:PROPOSED:2026-07-14": {
      "adjusted_close": null,
      "asset_role": "challenger",
      "carried_forward": false,
      "confidence": "low",
      "currency": null,
      "error": "No matching EOD result",
      "field_used": null,
      "is_final_eod_bar": null,
      "metadata": {},
      "price": null,
      "pricing_tier": "valuation_grade",
      "provider_exchange": null,
      "provider_symbol": "PROPOSED",
      "provider_timestamp": null,
      "provider_timezone": null,
      "raw_close": null,
      "requested_close_date": "2026-07-14",
      "returned_close_date": null,
      "selected_close": null,
      "selected_close_type": null,
      "source": "fmp",
      "source_detail": null,
      "status": "unresolved",
      "symbol": "PROPOSED",
      "verification": {
        "source": null,
        "status": "not_checked"
      }
    },
    "fmp:ROTATION:2026-07-14": {
      "adjusted_close": null,
      "asset_role": "challenger",
      "carried_forward": false,
      "confidence": "low",
      "currency": null,
      "error": "No matching EOD result",
      "field_used": null,
      "is_final_eod_bar": null,
      "metadata": {},
      "price": null,
      "pricing_tier": "valuation_grade",
      "provider_exchange": null,
      "provider_symbol": "ROTATION",
      "provider_timestamp": null,
      "provider_timezone": null,
      "raw_close": null,
      "requested_close_date": "2026-07-14",
      "returned_close_date": null,
      "selected_close": null,
      "selected_close_type": null,
      "source": "fmp",
      "source_detail": null,
      "status": "unresolved",
      "symbol": "ROTATION",
      "verification": {
        "source": null,
        "status": "not_checked"
      }
    },
    "fmp:TRADE:2026-07-14": {
      "adjusted_close": null,
      "asset_role": "challenger",
      "carried_forward": false,
      "confidence": "low",
      "currency": null,
      "error": "No matching EOD result",
      "field_used": null,
      "is_final_eod_bar": null,
      "metadata": {},
      "price": null,
      "pricing_tier": "valuation_grade",
      "provider_exchange": null,
      "provider_symbol": "TRADE",
      "provider_timestamp": null,
      "provider_timezone": null,
      "raw_close": null,
      "requested_close_date": "2026-07-14",
      "returned_close_date": null,
      "selected_close": null,
      "selected_close_type": null,
      "source": "fmp",
      "source_detail": null,
      "status": "unresolved",
      "symbol": "TRADE",
      "verification": {
        "source": null,
        "status": "not_checked"
      }
    },
    "fmp:WAS:2026-07-14": {
      "adjusted_close": null,
      "asset_role": "challenger",
      "carried_forward": false,
      "confidence": "low",
      "currency": null,
      "error": "No matching EOD result",
      "field_used": null,
      "is_final_eod_bar": null,
      "metadata": {},
      "price": null,
      "pricing_tier": "valuation_grade",
      "provider_exchange": null,
      "provider_symbol": "WAS",
      "provider_timestamp": null,
      "provider_timezone": null,
      "raw_close": null,
      "requested_close_date": "2026-07-14",
      "returned_close_date": null,
      "selected_close": null,
      "selected_close_type": null,
      "source": "fmp",
      "source_detail": null,
      "status": "unresolved",
      "symbol": "WAS",
      "verification": {
        "source": null,
        "status": "not_checked"
      }
    },
    "twelve_data:BOTZ:2026-07-14": {
      "adjusted_close": null,
      "asset_role": "challenger",
      "carried_forward": false,
      "confidence": "high",
      "currency": "USD",
      "error": null,
      "field_used": "close",
      "is_final_eod_bar": true,
      "metadata": {
        "endpoint": "time_series",
        "provider": "twelve_data"
      },
      "price": 35.88,
      "pricing_tier": "valuation_grade",
      "provider_exchange": "NASDAQ",
      "provider_symbol": "BOTZ",
      "provider_timestamp": null,
      "provider_timezone": "provider_daily_bar",
      "raw_close": 35.88,
      "requested_close_date": "2026-07-14",
      "returned_close_date": "2026-07-14",
      "selected_close": 35.88,
      "selected_close_type": "raw_close",
      "source": "twelve_data",
      "source_detail": "time_series",
      "status": "fresh_exact_unverified",
      "symbol": "BOTZ",
      "verification": {
        "source": null,
        "status": "not_checked"
      }
    },
    "twelve_data:BUG:2026-07-14": {
      "adjusted_close": null,
      "asset_role": "challenger",
      "carried_forward": false,
      "confidence": "high",
      "currency": "USD",
      "error": null,
      "field_used": "close",
      "is_final_eod_bar": true,
      "metadata": {
        "endpoint": "time_series",
        "provider": "twelve_data"
      },
      "price": 41.99,
      "pricing_tier": "valuation_grade",
      "provider_exchange": "NASDAQ",
      "provider_symbol": "BUG",
      "provider_timestamp": null,
      "provider_timezone": "provider_daily_bar",
      "raw_close": 41.99,
      "requested_close_date": "2026-07-14",
      "returned_close_date": "2026-07-14",
      "selected_close": 41.99,
      "selected_close_type": "raw_close",
      "source": "twelve_data",
      "source_detail": "time_series",
      "status": "fresh_exact_unverified",
      "symbol": "BUG",
      "verification": {
        "source": null,
        "status": "not_checked"
      }
    },
    "twelve_data:CIBR:2026-07-14": {
      "adjusted_close": null,
      "asset_role": "holding",
      "carried_forward": false,
      "confidence": "high",
      "currency": "USD",
      "error": null,
      "field_used": "close",
      "is_final_eod_bar": true,
      "metadata": {
        "endpoint": "time_series",
        "provider": "twelve_data"
      },
      "price": 94.73,
      "pricing_tier": "valuation_grade",
      "provider_exchange": "NASDAQ",
      "provider_symbol": "CIBR",
      "provider_timestamp": null,
      "provider_timezone": "provider_daily_bar",
      "raw_close": 94.73,
      "requested_close_date": "2026-07-14",
      "returned_close_date": "2026-07-14",
      "selected_close": 94.73,
      "selected_close_type": "raw_close",
      "source": "twelve_data",
      "source_detail": "time_series",
      "status": "fresh_exact_unverified",
      "symbol": "CIBR",
      "verification": {
        "source": null,
        "status": "not_checked"
      }
    },
    "twelve_data:CORN:2026-07-14": {
      "adjusted_close": null,
      "asset_role": "challenger",
      "carried_forward": false,
      "confidence": "high",
      "currency": "USD",
      "error": null,
      "field_used": "close",
      "is_final_eod_bar": true,
      "metadata": {
        "endpoint": "time_series",
        "provider": "twelve_data"
      },
      "price": 17.49,
      "pricing_tier": "valuation_grade",
      "provider_exchange": "NYSE",
      "provider_symbol": "CORN",
      "provider_timestamp": null,
      "provider_timezone": "provider_daily_bar",
      "raw_close": 17.49,
      "requested_close_date": "2026-07-14",
      "returned_close_date": "2026-07-14",
      "selected_close": 17.49,
      "selected_close_type": "raw_close",
      "source": "twelve_data",
      "source_detail": "time_series",
      "status": "fresh_exact_unverified",
      "symbol": "CORN",
      "verification": {
        "source": null,
        "status": "not_checked"
      }
    },
    "twelve_data:DBA:2026-07-14": {
      "adjusted_close": null,
      "asset_role": "challenger",
      "carried_forward": false,
      "confidence": "high",
      "currency": "USD",
      "error": null,
      "field_used": "close",
      "is_final_eod_bar": true,
      "metadata": {
        "endpoint": "time_series",
        "provider": "twelve_data"
      },
      "price": 27.63,
      "pricing_tier": "valuation_grade",
      "provider_exchange": "NYSE",
      "provider_symbol": "DBA",
      "provider_timestamp": null,
      "provider_timezone": "provider_daily_bar",
      "raw_close": 27.63,
      "requested_close_date": "2026-07-14",
      "returned_close_date": "2026-07-14",
      "selected_close": 27.63,
      "selected_close_type": "raw_close",
      "source": "twelve_data",
      "source_detail": "time_series",
      "status": "fresh_exact_unverified",
      "symbol": "DBA",
      "verification": {
        "source": null,
        "status": "not_checked"
      }
    },
    "twelve_data:DFEN:2026-07-14": {
      "adjusted_close": null,
      "asset_role": "holding",
      "carried_forward": false,
      "confidence": "high",
      "currency": "USD",
      "error": null,
      "field_used": "close",
      "is_final_eod_bar": true,
      "metadata": {
        "endpoint": "time_series",
        "provider": "twelve_data"
      },
      "price": 72.19,
      "pricing_tier": "valuation_grade",
      "provider_exchange": "NYSE",
      "provider_symbol": "DFEN",
      "provider_timestamp": null,
      "provider_timezone": "provider_daily_bar",
      "raw_close": 72.19,
      "requested_close_date": "2026-07-14",
      "returned_close_date": "2026-07-14",
      "selected_close": 72.19,
      "selected_close_type": "raw_close",
      "source": "twelve_data",
      "source_detail": "time_series",
      "status": "fresh_exact_unverified",
      "symbol": "DFEN",
      "verification": {
        "source": null,
        "status": "not_checked"
      }
    },
    "twelve_data:EFA:2026-07-14": {
      "adjusted_close": null,
      "asset_role": "challenger",
      "carried_forward": false,
      "confidence": "high",
      "currency": "USD",
      "error": null,
      "field_used": "close",
      "is_final_eod_bar": true,
      "metadata": {
        "endpoint": "time_series",
        "provider": "twelve_data"
      },
      "price": 103.96,
      "pricing_tier": "valuation_grade",
      "provider_exchange": "NYSE",
      "provider_symbol": "EFA",
      "provider_timestamp": null,
      "provider_timezone": "provider_daily_bar",
      "raw_close": 103.96,
      "requested_close_date": "2026-07-14",
      "returned_close_date": "2026-07-14",
      "selected_close": 103.96,
      "selected_close_type": "raw_close",
      "source": "twelve_data",
      "source_detail": "time_series",
      "status": "fresh_exact_unverified",
      "symbol": "EFA",
      "verification": {
        "source": null,
        "status": "not_checked"
      }
    },
    "twelve_data:FINX:2026-07-14": {
      "adjusted_close": null,
      "asset_role": "challenger",
      "carried_forward": false,
      "confidence": "high",
      "currency": "USD",
      "error": null,
      "field_used": "close",
      "is_final_eod_bar": true,
      "metadata": {
        "endpoint": "time_series",
        "provider": "twelve_data"
      },
      "price": 25.49,
      "pricing_tier": "valuation_grade",
      "provider_exchange": "NASDAQ",
      "provider_symbol": "FINX",
      "provider_timestamp": null,
      "provider_timezone": "provider_daily_bar",
      "raw_close": 25.49,
      "requested_close_date": "2026-07-14",
      "returned_close_date": "2026-07-14",
      "selected_close": 25.49,
      "selected_close_type": "raw_close",
      "source": "twelve_data",
      "source_detail": "time_series",
      "status": "fresh_exact_unverified",
      "symbol": "FINX",
      "verification": {
        "source": null,
        "status": "not_checked"
      }
    },
    "twelve_data:GENERATED:2026-07-14": {
      "adjusted_close": null,
      "asset_role": "challenger",
      "carried_forward": false,
      "confidence": "low",
      "currency": null,
      "error": "HTTP Error 404: Not Found",
      "field_used": null,
      "is_final_eod_bar": null,
      "metadata": {},
      "price": null,
      "pricing_tier": "valuation_grade",
      "provider_exchange": null,
      "provider_symbol": "GENERATED",
      "provider_timestamp": null,
      "provider_timezone": null,
      "raw_close": null,
      "requested_close_date": "2026-07-14",
      "returned_close_date": null,
      "selected_close": null,
      "selected_close_type": null,
      "source": "twelve_data",
      "source_detail": null,
      "status": "unresolved",
      "symbol": "GENERATED",
      "verification": {
        "source": null,
        "status": "not_checked"
      }
    },
    "twelve_data:GRID:2026-07-14": {
      "adjusted_close": null,
      "asset_role": "challenger",
      "carried_forward": false,
      "confidence": "high",
      "currency": "USD",
      "error": null,
      "field_used": "close",
      "is_final_eod_bar": true,
      "metadata": {
        "endpoint": "time_series",
        "provider": "twelve_data"
      },
      "price": 183.71001,
      "pricing_tier": "valuation_grade",
      "provider_exchange": "NASDAQ",
      "provider_symbol": "GRID",
      "provider_timestamp": null,
      "provider_timezone": "provider_daily_bar",
      "raw_close": 183.71001,
      "requested_close_date": "2026-07-14",
      "returned_close_date": "2026-07-14",
      "selected_close": 183.71001,
      "selected_close_type": "raw_close",
      "source": "twelve_data",
      "source_detail": "time_series",
      "status": "fresh_exact_unverified",
      "symbol": "GRID",
      "verification": {
        "source": null,
        "status": "not_checked"
      }
    },
    "twelve_data:GSG:2026-07-14": {
      "adjusted_close": null,
      "asset_role": "holding",
      "carried_forward": false,
      "confidence": "high",
      "currency": "USD",
      "error": null,
      "field_used": "close",
      "is_final_eod_bar": true,
      "metadata": {
        "endpoint": "time_series",
        "provider": "twelve_data"
      },
      "price": 31.0,
      "pricing_tier": "valuation_grade",
      "provider_exchange": "NYSE",
      "provider_symbol": "GSG",
      "provider_timestamp": null,
      "provider_timezone": "provider_daily_bar",
      "raw_close": 31.0,
      "requested_close_date": "2026-07-14",
      "returned_close_date": "2026-07-14",
      "selected_close": 31.0,
      "selected_close_type": "raw_close",
      "source": "twelve_data",
      "source_detail": "time_series",
      "status": "fresh_exact_unverified",
      "symbol": "GSG",
      "verification": {
        "source": null,
        "status": "not_checked"
      }
    },
    "twelve_data:IAI:2026-07-14": {
      "adjusted_close": null,
      "asset_role": "challenger",
      "carried_forward": false,
      "confidence": "high",
      "currency": "USD",
      "error": null,
      "field_used": "close",
      "is_final_eod_bar": true,
      "metadata": {
        "endpoint": "time_series",
        "provider": "twelve_data"
      },
      "price": 193.47,
      "pricing_tier": "valuation_grade",
      "provider_exchange": "NYSE",
      "provider_symbol": "IAI",
      "provider_timestamp": null,
      "provider_timezone": "provider_daily_bar",
      "raw_close": 193.47,
      "requested_close_date": "2026-07-14",
      "returned_close_date": "2026-07-14",
      "selected_close": 193.47,
      "selected_close_type": "raw_close",
      "source": "twelve_data",
      "source_detail": "time_series",
      "status": "fresh_exact_unverified",
      "symbol": "IAI",
      "verification": {
        "source": null,
        "status": "not_checked"
      }
    },
    "twelve_data:IBB:2026-07-14": {
      "adjusted_close": null,
      "asset_role": "challenger",
      "carried_forward": false,
      "confidence": "high",
      "currency": "USD",
      "error": null,
      "field_used": "close",
      "is_final_eod_bar": true,
      "metadata": {
        "endpoint": "time_series",
        "provider": "twelve_data"
      },
      "price": 188.67,
      "pricing_tier": "valuation_grade",
      "provider_exchange": "NASDAQ",
      "provider_symbol": "IBB",
      "provider_timestamp": null,
      "provider_timezone": "provider_daily_bar",
      "raw_close": 188.67,
      "requested_close_date": "2026-07-14",
      "returned_close_date": "2026-07-14",
      "selected_close": 188.67,
      "selected_close_type": "raw_close",
      "source": "twelve_data",
      "source_detail": "time_series",
      "status": "fresh_exact_unverified",
      "symbol": "IBB",
      "verification": {
        "source": null,
        "status": "not_checked"
      }
    },
    "twelve_data:IEFA:2026-07-14": {
      "adjusted_close": null,
      "asset_role": "holding",
      "carried_forward": false,
      "confidence": "high",
      "currency": "USD",
      "error": null,
      "field_used": "close",
      "is_final_eod_bar": true,
      "metadata": {
        "endpoint": "time_series",
        "provider": "twelve_data"
      },
      "price": 96.89,
      "pricing_tier": "valuation_grade",
      "provider_exchange": "CBOE",
      "provider_symbol": "IEFA",
      "provider_timestamp": null,
      "provider_timezone": "provider_daily_bar",
      "raw_close": 96.89,
      "requested_close_date": "2026-07-14",
      "returned_close_date": "2026-07-14",
      "selected_close": 96.89,
      "selected_close_type": "raw_close",
      "source": "twelve_data",
      "source_detail": "time_series",
      "status": "fresh_exact_unverified",
      "symbol": "IEFA",
      "verification": {
        "source": null,
        "status": "not_checked"
      }
    },
    "twelve_data:INTENT:2026-07-14": {
      "adjusted_close": null,
      "asset_role": "challenger",
      "carried_forward": false,
      "confidence": "low",
      "currency": null,
      "error": "HTTP Error 404: Not Found",
      "field_used": null,
      "is_final_eod_bar": null,
      "metadata": {},
      "price": null,
      "pricing_tier": "valuation_grade",
      "provider_exchange": null,
      "provider_symbol": "INTENT",
      "provider_timestamp": null,
      "provider_timezone": null,
      "raw_close": null,
      "requested_close_date": "2026-07-14",
      "returned_close_date": null,
      "selected_close": null,
      "selected_close_type": null,
      "source": "twelve_data",
      "source_detail": null,
      "status": "unresolved",
      "symbol": "INTENT",
      "verification": {
        "source": null,
        "status": "not_checked"
      }
    },
    "twelve_data:IRBO:2026-07-14": {
      "adjusted_close": null,
      "asset_role": "challenger",
      "carried_forward": false,
      "confidence": "medium",
      "currency": "USD",
      "error": null,
      "field_used": "close",
      "is_final_eod_bar": true,
      "metadata": {
        "endpoint": "time_series",
        "provider": "twelve_data"
      },
      "price": 72.5,
      "pricing_tier": "valuation_grade",
      "provider_exchange": "NYSE",
      "provider_symbol": "IRBO",
      "provider_timestamp": null,
      "provider_timezone": "provider_daily_bar",
      "raw_close": 72.5,
      "requested_close_date": "2026-07-14",
      "returned_close_date": "2026-07-10",
      "selected_close": 72.5,
      "selected_close_type": "raw_close",
      "source": "twelve_data",
      "source_detail": "time_series_latest",
      "status": "prior_valid_close",
      "symbol": "IRBO",
      "verification": {
        "source": null,
        "status": "not_checked"
      }
    },
    "twelve_data:ITA:2026-07-14": {
      "adjusted_close": null,
      "asset_role": "challenger",
      "carried_forward": false,
      "confidence": "high",
      "currency": "USD",
      "error": null,
      "field_used": "close",
      "is_final_eod_bar": true,
      "metadata": {
        "endpoint": "time_series",
        "provider": "twelve_data"
      },
      "price": 235.27,
      "pricing_tier": "valuation_grade",
      "provider_exchange": "CBOE",
      "provider_symbol": "ITA",
      "provider_timestamp": null,
      "provider_timezone": "provider_daily_bar",
      "raw_close": 235.27,
      "requested_close_date": "2026-07-14",
      "returned_close_date": "2026-07-14",
      "selected_close": 235.27,
      "selected_close_type": "raw_close",
      "source": "twelve_data",
      "source_detail": "time_series",
      "status": "fresh_exact_unverified",
      "symbol": "ITA",
      "verification": {
        "source": null,
        "status": "not_checked"
      }
    },
    "twelve_data:IWM:2026-07-14": {
      "adjusted_close": null,
      "asset_role": "challenger",
      "carried_forward": false,
      "confidence": "high",
      "currency": "USD",
      "error": null,
      "field_used": "close",
      "is_final_eod_bar": true,
      "metadata": {
        "endpoint": "time_series",
        "provider": "twelve_data"
      },
      "price": 294.51001,
      "pricing_tier": "valuation_grade",
      "provider_exchange": "NYSE",
      "provider_symbol": "IWM",
      "provider_timestamp": null,
      "provider_timezone": "provider_daily_bar",
      "raw_close": 294.51001,
      "requested_close_date": "2026-07-14",
      "returned_close_date": "2026-07-14",
      "selected_close": 294.51001,
      "selected_close_type": "raw_close",
      "source": "twelve_data",
      "source_detail": "time_series",
      "status": "fresh_exact_unverified",
      "symbol": "IWM",
      "verification": {
        "source": null,
        "status": "not_checked"
      }
    },
    "twelve_data:KCE:2026-07-14": {
      "adjusted_close": null,
      "asset_role": "challenger",
      "carried_forward": false,
      "confidence": "high",
      "currency": "USD",
      "error": null,
      "field_used": "close",
      "is_final_eod_bar": true,
      "metadata": {
        "endpoint": "time_series",
        "provider": "twelve_data"
      },
      "price": 157.666,
      "pricing_tier": "valuation_grade",
      "provider_exchange": "NYSE",
      "provider_symbol": "KCE",
      "provider_timestamp": null,
      "provider_timezone": "provider_daily_bar",
      "raw_close": 157.666,
      "requested_close_date": "2026-07-14",
      "returned_close_date": "2026-07-14",
      "selected_close": 157.666,
      "selected_close_type": "raw_close",
      "source": "twelve_data",
      "source_detail": "time_series",
      "status": "fresh_exact_unverified",
      "symbol": "KCE",
      "verification": {
        "source": null,
        "status": "not_checked"
      }
    },
    "twelve_data:NLR:2026-07-14": {
      "adjusted_close": null,
      "asset_role": "challenger",
      "carried_forward": false,
      "confidence": "high",
      "currency": "USD",
      "error": null,
      "field_used": "close",
      "is_final_eod_bar": true,
      "metadata": {
        "endpoint": "time_series",
        "provider": "twelve_data"
      },
      "price": 111.37,
      "pricing_tier": "valuation_grade",
      "provider_exchange": "NYSE",
      "provider_symbol": "NLR",
      "provider_timestamp": null,
      "provider_timezone": "provider_daily_bar",
      "raw_close": 111.37,
      "requested_close_date": "2026-07-14",
      "returned_close_date": "2026-07-14",
      "selected_close": 111.37,
      "selected_close_type": "raw_close",
      "source": "twelve_data",
      "source_detail": "time_series",
      "status": "fresh_exact_unverified",
      "symbol": "NLR",
      "verification": {
        "source": null,
        "status": "not_checked"
      }
    },
    "twelve_data:NUCL:2026-07-14": {
      "adjusted_close": null,
      "asset_role": "challenger",
      "carried_forward": false,
      "confidence": "high",
      "currency": "USD",
      "error": null,
      "field_used": "close",
      "is_final_eod_bar": true,
      "metadata": {
        "endpoint": "time_series",
        "provider": "twelve_data"
      },
      "price": 6.26,
      "pricing_tier": "valuation_grade",
      "provider_exchange": "NASDAQ",
      "provider_symbol": "NUCL",
      "provider_timestamp": null,
      "provider_timezone": "provider_daily_bar",
      "raw_close": 6.26,
      "requested_close_date": "2026-07-14",
      "returned_close_date": "2026-07-14",
      "selected_close": 6.26,
      "selected_close_type": "raw_close",
      "source": "twelve_data",
      "source_detail": "time_series",
      "status": "fresh_exact_unverified",
      "symbol": "NUCL",
      "verification": {
        "source": null,
        "status": "not_checked"
      }
    },
    "twelve_data:PAVE:2026-07-14": {
      "adjusted_close": null,
      "asset_role": "holding",
      "carried_forward": false,
      "confidence": "high",
      "currency": "USD",
      "error": null,
      "field_used": "close",
      "is_final_eod_bar": true,
      "metadata": {
        "endpoint": "time_series",
        "provider": "twelve_data"
      },
      "price": 56.71,
      "pricing_tier": "valuation_grade",
      "provider_exchange": "Cboe BZX",
      "provider_symbol": "PAVE",
      "provider_timestamp": null,
      "provider_timezone": "provider_daily_bar",
      "raw_close": 56.71,
      "requested_close_date": "2026-07-14",
      "returned_close_date": "2026-07-14",
      "selected_close": 56.71,
      "selected_close_type": "raw_close",
      "source": "twelve_data",
      "source_detail": "time_series",
      "status": "fresh_exact_unverified",
      "symbol": "PAVE",
      "verification": {
        "source": null,
        "status": "not_checked"
      }
    },
    "twelve_data:PPA:2026-07-14": {
      "adjusted_close": null,
      "asset_role": "challenger",
      "carried_forward": false,
      "confidence": "high",
      "currency": "USD",
      "error": null,
      "field_used": "close",
      "is_final_eod_bar": true,
      "metadata": {
        "endpoint": "time_series",
        "provider": "twelve_data"
      },
      "price": 171.7,
      "pricing_tier": "valuation_grade",
      "provider_exchange": "NYSE Arca",
      "provider_symbol": "PPA",
      "provider_timestamp": null,
      "provider_timezone": "provider_daily_bar",
      "raw_close": 171.7,
      "requested_close_date": "2026-07-14",
      "returned_close_date": "2026-07-14",
      "selected_close": 171.7,
      "selected_close_type": "raw_close",
      "source": "twelve_data",
      "source_detail": "time_series",
      "status": "fresh_exact_unverified",
      "symbol": "PPA",
      "verification": {
        "source": null,
        "status": "not_checked"
      }
    },
    "twelve_data:PROPOSED:2026-07-14": {
      "adjusted_close": null,
      "asset_role": "challenger",
      "carried_forward": false,
      "confidence": "low",
      "currency": null,
      "error": "HTTP Error 404: Not Found",
      "field_used": null,
      "is_final_eod_bar": null,
      "metadata": {},
      "price": null,
      "pricing_tier": "valuation_grade",
      "provider_exchange": null,
      "provider_symbol": "PROPOSED",
      "provider_timestamp": null,
      "provider_timezone": null,
      "raw_close": null,
      "requested_close_date": "2026-07-14",
      "returned_close_date": null,
      "selected_close": null,
      "selected_close_type": null,
      "source": "twelve_data",
      "source_detail": null,
      "status": "unresolved",
      "symbol": "PROPOSED",
      "verification": {
        "source": null,
        "status": "not_checked"
      }
    },
    "twelve_data:QUAL:2026-07-14": {
      "adjusted_close": null,
      "asset_role": "challenger",
      "carried_forward": false,
      "confidence": "high",
      "currency": "USD",
      "error": null,
      "field_used": "close",
      "is_final_eod_bar": true,
      "metadata": {
        "endpoint": "time_series",
        "provider": "twelve_data"
      },
      "price": 219.24001,
      "pricing_tier": "valuation_grade",
      "provider_exchange": "CBOE",
      "provider_symbol": "QUAL",
      "provider_timestamp": null,
      "provider_timezone": "provider_daily_bar",
      "raw_close": 219.24001,
      "requested_close_date": "2026-07-14",
      "returned_close_date": "2026-07-14",
      "selected_close": 219.24001,
      "selected_close_type": "raw_close",
      "source": "twelve_data",
      "source_detail": "time_series",
      "status": "fresh_exact_unverified",
      "symbol": "QUAL",
      "verification": {
        "source": null,
        "status": "not_checked"
      }
    },
    "twelve_data:ROBO:2026-07-14": {
      "adjusted_close": null,
      "asset_role": "challenger",
      "carried_forward": false,
      "confidence": "high",
      "currency": "USD",
      "error": null,
      "field_used": "close",
      "is_final_eod_bar": true,
      "metadata": {
        "endpoint": "time_series",
        "provider": "twelve_data"
      },
      "price": 80.78,
      "pricing_tier": "valuation_grade",
      "provider_exchange": "NYSE",
      "provider_symbol": "ROBO",
      "provider_timestamp": null,
      "provider_timezone": "provider_daily_bar",
      "raw_close": 80.78,
      "requested_close_date": "2026-07-14",
      "returned_close_date": "2026-07-14",
      "selected_close": 80.78,
      "selected_close_type": "raw_close",
      "source": "twelve_data",
      "source_detail": "time_series",
      "status": "fresh_exact_unverified",
      "symbol": "ROBO",
      "verification": {
        "source": null,
        "status": "not_checked"
      }
    },
    "twelve_data:ROTATION:2026-07-14": {
      "adjusted_close": null,
      "asset_role": "challenger",
      "carried_forward": false,
      "confidence": "low",
      "currency": null,
      "error": "HTTP Error 404: Not Found",
      "field_used": null,
      "is_final_eod_bar": null,
      "metadata": {},
      "price": null,
      "pricing_tier": "valuation_grade",
      "provider_exchange": null,
      "provider_symbol": "ROTATION",
      "provider_timestamp": null,
      "provider_timezone": null,
      "raw_close": null,
      "requested_close_date": "2026-07-14",
      "returned_close_date": null,
      "selected_close": null,
      "selected_close_type": null,
      "source": "twelve_data",
      "source_detail": null,
      "status": "unresolved",
      "symbol": "ROTATION",
      "verification": {
        "source": null,
        "status": "not_checked"
      }
    },
    "twelve_data:SMH:2026-07-14": {
      "adjusted_close": null,
      "asset_role": "holding",
      "carried_forward": false,
      "confidence": "high",
      "currency": "USD",
      "error": null,
      "field_used": "close",
      "is_final_eod_bar": true,
      "metadata": {
        "endpoint": "time_series",
        "provider": "twelve_data"
      },
      "price": 600.31,
      "pricing_tier": "valuation_grade",
      "provider_exchange": "NASDAQ",
      "provider_symbol": "SMH",
      "provider_timestamp": null,
      "provider_timezone": "provider_daily_bar",
      "raw_close": 600.31,
      "requested_close_date": "2026-07-14",
      "returned_close_date": "2026-07-14",
      "selected_close": 600.31,
      "selected_close_type": "raw_close",
      "source": "twelve_data",
      "source_detail": "time_series",
      "status": "fresh_exact_unverified",
      "symbol": "SMH",
      "verification": {
        "source": null,
        "status": "not_checked"
      }
    },
    "twelve_data:SOXX:2026-07-14": {
      "adjusted_close": null,
      "asset_role": "challenger",
      "carried_forward": false,
      "confidence": "high",
      "currency": "USD",
      "error": null,
      "field_used": "close",
      "is_final_eod_bar": true,
      "metadata": {
        "endpoint": "time_series",
        "provider": "twelve_data"
      },
      "price": 567.91998,
      "pricing_tier": "valuation_grade",
      "provider_exchange": "NASDAQ",
      "provider_symbol": "SOXX",
      "provider_timestamp": null,
      "provider_timezone": "provider_daily_bar",
      "raw_close": 567.91998,
      "requested_close_date": "2026-07-14",
      "returned_close_date": "2026-07-14",
      "selected_close": 567.91998,
      "selected_close_type": "raw_close",
      "source": "twelve_data",
      "source_detail": "time_series",
      "status": "fresh_exact_unverified",
      "symbol": "SOXX",
      "verification": {
        "source": null,
        "status": "not_checked"
      }
    },
    "twelve_data:SPY:2026-07-14": {
      "adjusted_close": null,
      "asset_role": "holding",
      "carried_forward": false,
      "confidence": "high",
      "currency": "USD",
      "error": null,
      "field_used": "close",
      "is_final_eod_bar": true,
      "metadata": {
        "endpoint": "time_series",
        "provider": "twelve_data"
      },
      "price": 751.83002,
      "pricing_tier": "valuation_grade",
      "provider_exchange": "NYSE Arca",
      "provider_symbol": "SPY",
      "provider_timestamp": null,
      "provider_timezone": "provider_daily_bar",
      "raw_close": 751.83002,
      "requested_close_date": "2026-07-14",
      "returned_close_date": "2026-07-14",
      "selected_close": 751.83002,
      "selected_close_type": "raw_close",
      "source": "twelve_data",
      "source_detail": "time_series",
      "status": "fresh_exact_unverified",
      "symbol": "SPY",
      "verification": {
        "source": null,
        "status": "not_checked"
      }
    },
    "twelve_data:TRADE:2026-07-14": {
      "adjusted_close": null,
      "asset_role": "challenger",
      "carried_forward": false,
      "confidence": "low",
      "currency": null,
      "error": "HTTP Error 404: Not Found",
      "field_used": null,
      "is_final_eod_bar": null,
      "metadata": {},
      "price": null,
      "pricing_tier": "valuation_grade",
      "provider_exchange": null,
      "provider_symbol": "TRADE",
      "provider_timestamp": null,
      "provider_timezone": null,
      "raw_close": null,
      "requested_close_date": "2026-07-14",
      "returned_close_date": null,
      "selected_close": null,
      "selected_close_type": null,
      "source": "twelve_data",
      "source_detail": null,
      "status": "unresolved",
      "symbol": "TRADE",
      "verification": {
        "source": null,
        "status": "not_checked"
      }
    },
    "twelve_data:URA:2026-07-14": {
      "adjusted_close": null,
      "asset_role": "challenger",
      "carried_forward": false,
      "confidence": "high",
      "currency": "USD",
      "error": null,
      "field_used": "close",
      "is_final_eod_bar": true,
      "metadata": {
        "endpoint": "time_series",
        "provider": "twelve_data"
      },
      "price": 41.55,
      "pricing_tier": "valuation_grade",
      "provider_exchange": "NYSE",
      "provider_symbol": "URA",
      "provider_timestamp": null,
      "provider_timezone": "provider_daily_bar",
      "raw_close": 41.55,
      "requested_close_date": "2026-07-14",
      "returned_close_date": "2026-07-14",
      "selected_close": 41.55,
      "selected_close_type": "raw_close",
      "source": "twelve_data",
      "source_detail": "time_series",
      "status": "fresh_exact_unverified",
      "symbol": "URA",
      "verification": {
        "source": null,
        "status": "not_checked"
      }
    },
    "twelve_data:URNM:2026-07-14": {
      "adjusted_close": null,
      "asset_role": "holding",
      "carried_forward": false,
      "confidence": "high",
      "currency": "USD",
      "error": null,
      "field_used": "close",
      "is_final_eod_bar": true,
      "metadata": {
        "endpoint": "time_series",
        "provider": "twelve_data"
      },
      "price": 51.59,
      "pricing_tier": "valuation_grade",
      "provider_exchange": "NYSE Arca",
      "provider_symbol": "URNM",
      "provider_timestamp": null,
      "provider_timezone": "provider_daily_bar",
      "raw_close": 51.59,
      "requested_close_date": "2026-07-14",
      "returned_close_date": "2026-07-14",
      "selected_close": 51.59,
      "selected_close_type": "raw_close",
      "source": "twelve_data",
      "source_detail": "time_series",
      "status": "fresh_exact_unverified",
      "symbol": "URNM",
      "verification": {
        "source": null,
        "status": "not_checked"
      }
    },
    "twelve_data:VHT:2026-07-14": {
      "adjusted_close": null,
      "asset_role": "challenger",
      "carried_forward": false,
      "confidence": "high",
      "currency": "USD",
      "error": null,
      "field_used": "close",
      "is_final_eod_bar": true,
      "metadata": {
        "endpoint": "time_series",
        "provider": "twelve_data"
      },
      "price": 298.59,
      "pricing_tier": "valuation_grade",
      "provider_exchange": "NYSE",
      "provider_symbol": "VHT",
      "provider_timestamp": null,
      "provider_timezone": "provider_daily_bar",
      "raw_close": 298.59,
      "requested_close_date": "2026-07-14",
      "returned_close_date": "2026-07-14",
      "selected_close": 298.59,
      "selected_close_type": "raw_close",
      "source": "twelve_data",
      "source_detail": "time_series",
      "status": "fresh_exact_unverified",
      "symbol": "VHT",
      "verification": {
        "source": null,
        "status": "not_checked"
      }
    },
    "twelve_data:VPU:2026-07-14": {
      "adjusted_close": null,
      "asset_role": "challenger",
      "carried_forward": false,
      "confidence": "high",
      "currency": "USD",
      "error": null,
      "field_used": "close",
      "is_final_eod_bar": true,
      "metadata": {
        "endpoint": "time_series",
        "provider": "twelve_data"
      },
      "price": 197.39,
      "pricing_tier": "valuation_grade",
      "provider_exchange": "NYSE",
      "provider_symbol": "VPU",
      "provider_timestamp": null,
      "provider_timezone": "provider_daily_bar",
      "raw_close": 197.39,
      "requested_close_date": "2026-07-14",
      "returned_close_date": "2026-07-14",
      "selected_close": 197.39,
      "selected_close_type": "raw_close",
      "source": "twelve_data",
      "source_detail": "time_series",
      "status": "fresh_exact_unverified",
      "symbol": "VPU",
      "verification": {
        "source": null,
        "status": "not_checked"
      }
    },
    "twelve_data:WAS:2026-07-14": {
      "adjusted_close": null,
      "asset_role": "challenger",
      "carried_forward": false,
      "confidence": "low",
      "currency": null,
      "error": "HTTP Error 404: Not Found",
      "field_used": null,
      "is_final_eod_bar": null,
      "metadata": {},
      "price": null,
      "pricing_tier": "valuation_grade",
      "provider_exchange": null,
      "provider_symbol": "WAS",
      "provider_timestamp": null,
      "provider_timezone": null,
      "raw_close": null,
      "requested_close_date": "2026-07-14",
      "returned_close_date": null,
      "selected_close": null,
      "selected_close_type": null,
      "source": "twelve_data",
      "source_detail": null,
      "status": "unresolved",
      "symbol": "WAS",
      "verification": {
        "source": null,
        "status": "not_checked"
      }
    },
    "twelve_data:XBI:2026-07-14": {
      "adjusted_close": null,
      "asset_role": "challenger",
      "carried_forward": false,
      "confidence": "high",
      "currency": "USD",
      "error": null,
      "field_used": "close",
      "is_final_eod_bar": true,
      "metadata": {
        "endpoint": "time_series",
        "provider": "twelve_data"
      },
      "price": 155.45,
      "pricing_tier": "valuation_grade",
      "provider_exchange": "NYSE",
      "provider_symbol": "XBI",
      "provider_timestamp": null,
      "provider_timezone": "provider_daily_bar",
      "raw_close": 155.45,
      "requested_close_date": "2026-07-14",
      "returned_close_date": "2026-07-14",
      "selected_close": 155.45,
      "selected_close_type": "raw_close",
      "source": "twelve_data",
      "source_detail": "time_series",
      "status": "fresh_exact_unverified",
      "symbol": "XBI",
      "verification": {
        "source": null,
        "status": "not_checked"
      }
    },
    "twelve_data:XLU:2026-07-14": {
      "adjusted_close": null,
      "asset_role": "holding",
      "carried_forward": false,
      "confidence": "high",
      "currency": "USD",
      "error": null,
      "field_used": "close",
      "is_final_eod_bar": true,
      "metadata": {
        "endpoint": "time_series",
        "provider": "twelve_data"
      },
      "price": 45.69,
      "pricing_tier": "valuation_grade",
      "provider_exchange": "NYSE",
      "provider_symbol": "XLU",
      "provider_timestamp": null,
      "provider_timezone": "provider_daily_bar",
      "raw_close": 45.69,
      "requested_close_date": "2026-07-14",
      "returned_close_date": "2026-07-14",
      "selected_close": 45.69,
      "selected_close_type": "raw_close",
      "source": "twelve_data",
      "source_detail": "time_series",
      "status": "fresh_exact_unverified",
      "symbol": "XLU",
      "verification": {
        "source": null,
        "status": "not_checked"
      }
    },
    "twelve_data:XLV:2026-07-14": {
      "adjusted_close": null,
      "asset_role": "challenger",
      "carried_forward": false,
      "confidence": "high",
      "currency": "USD",
      "error": null,
      "field_used": "close",
      "is_final_eod_bar": true,
      "metadata": {
        "endpoint": "time_series",
        "provider": "twelve_data"
      },
      "price": 158.28999,
      "pricing_tier": "valuation_grade",
      "provider_exchange": "NYSE",
      "provider_symbol": "XLV",
      "provider_timestamp": null,
      "provider_timezone": "provider_daily_bar",
      "raw_close": 158.28999,
      "requested_close_date": "2026-07-14",
      "returned_close_date": "2026-07-14",
      "selected_close": 158.28999,
      "selected_close_type": "raw_close",
      "source": "twelve_data",
      "source_detail": "time_series",
      "status": "fresh_exact_unverified",
      "symbol": "XLV",
      "verification": {
        "source": null,
        "status": "not_checked"
      }
    },
    "yahoo_history:GENERATED:2026-07-14": {
      "adjusted_close": null,
      "asset_role": "challenger",
      "carried_forward": false,
      "confidence": "low",
      "currency": null,
      "error": "HTTP Error 404: Not Found",
      "field_used": null,
      "is_final_eod_bar": null,
      "metadata": {},
      "price": null,
      "pricing_tier": "valuation_grade",
      "provider_exchange": null,
      "provider_symbol": "GENERATED",
      "provider_timestamp": null,
      "provider_timezone": null,
      "raw_close": null,
      "requested_close_date": "2026-07-14",
      "returned_close_date": null,
      "selected_close": null,
      "selected_close_type": null,
      "source": "yahoo_history",
      "source_detail": "query1_chart_v8",
      "status": "unresolved",
      "symbol": "GENERATED",
      "verification": {
        "source": null,
        "status": "not_checked"
      }
    },
    "yahoo_history:INTENT:2026-07-14": {
      "adjusted_close": null,
      "asset_role": "challenger",
      "carried_forward": false,
      "confidence": "low",
      "currency": null,
      "error": "HTTP Error 404: Not Found",
      "field_used": null,
      "is_final_eod_bar": null,
      "metadata": {},
      "price": null,
      "pricing_tier": "valuation_grade",
      "provider_exchange": null,
      "provider_symbol": "INTENT",
      "provider_timestamp": null,
      "provider_timezone": null,
      "raw_close": null,
      "requested_close_date": "2026-07-14",
      "returned_close_date": null,
      "selected_close": null,
      "selected_close_type": null,
      "source": "yahoo_history",
      "source_detail": "query1_chart_v8",
      "status": "unresolved",
      "symbol": "INTENT",
      "verification": {
        "source": null,
        "status": "not_checked"
      }
    },
    "yahoo_history:PROPOSED:2026-07-14": {
      "adjusted_close": null,
      "asset_role": "challenger",
      "carried_forward": false,
      "confidence": "low",
      "currency": null,
      "error": "HTTP Error 404: Not Found",
      "field_used": null,
      "is_final_eod_bar": null,
      "metadata": {},
      "price": null,
      "pricing_tier": "valuation_grade",
      "provider_exchange": null,
      "provider_symbol": "PROPOSED",
      "provider_timestamp": null,
      "provider_timezone": null,
      "raw_close": null,
      "requested_close_date": "2026-07-14",
      "returned_close_date": null,
      "selected_close": null,
      "selected_close_type": null,
      "source": "yahoo_history",
      "source_detail": "query1_chart_v8",
      "status": "unresolved",
      "symbol": "PROPOSED",
      "verification": {
        "source": null,
        "status": "not_checked"
      }
    },
    "yahoo_history:ROTATION:2026-07-14": {
      "adjusted_close": null,
      "asset_role": "challenger",
      "carried_forward": false,
      "confidence": "low",
      "currency": null,
      "error": "HTTP Error 404: Not Found",
      "field_used": null,
      "is_final_eod_bar": null,
      "metadata": {},
      "price": null,
      "pricing_tier": "valuation_grade",
      "provider_exchange": null,
      "provider_symbol": "ROTATION",
      "provider_timestamp": null,
      "provider_timezone": null,
      "raw_close": null,
      "requested_close_date": "2026-07-14",
      "returned_close_date": null,
      "selected_close": null,
      "selected_close_type": null,
      "source": "yahoo_history",
      "source_detail": "query1_chart_v8",
      "status": "unresolved",
      "symbol": "ROTATION",
      "verification": {
        "source": null,
        "status": "not_checked"
      }
    },
    "yahoo_history:TRADE:2026-07-14": {
      "adjusted_close": null,
      "asset_role": "challenger",
      "carried_forward": false,
      "confidence": "low",
      "currency": null,
      "error": "HTTP Error 404: Not Found",
      "field_used": null,
      "is_final_eod_bar": null,
      "metadata": {},
      "price": null,
      "pricing_tier": "valuation_grade",
      "provider_exchange": null,
      "provider_symbol": "TRADE",
      "provider_timestamp": null,
      "provider_timezone": null,
      "raw_close": null,
      "requested_close_date": "2026-07-14",
      "returned_close_date": null,
      "selected_close": null,
      "selected_close_type": null,
      "source": "yahoo_history",
      "source_detail": "query1_chart_v8",
      "status": "unresolved",
      "symbol": "TRADE",
      "verification": {
        "source": null,
        "status": "not_checked"
      }
    },
    "yahoo_history:WAS:2026-07-14": {
      "adjusted_close": null,
      "asset_role": "challenger",
      "carried_forward": false,
      "confidence": "low",
      "currency": null,
      "error": "Yahoo chart endpoint returned no valid close values.",
      "field_used": null,
      "is_final_eod_bar": null,
      "metadata": {},
      "price": null,
      "pricing_tier": "valuation_grade",
      "provider_exchange": "NMS",
      "provider_symbol": "WAS",
      "provider_timestamp": null,
      "provider_timezone": null,
      "raw_close": null,
      "requested_close_date": "2026-07-14",
      "returned_close_date": null,
      "selected_close": null,
      "selected_close_type": null,
      "source": "yahoo_history",
      "source_detail": "query1_chart_v8",
      "status": "unresolved",
      "symbol": "WAS",
      "verification": {
        "source": null,
        "status": "not_checked"
      }
    }
  }
}