{
  "breadth_trend": "mixed",
  "confidence_trend": "rising",
  "cross_asset_confirmation": "mixed",
  "current_confidence": 0.72,
  "current_regime": "Risk-on narrow leadership",
  "decision_rule": "Do not rotate aggressively unless a regime shift persists for at least two runs or cross-asset confirmation becomes broad.",
  "failed_rotation_count": 0,
  "last_major_shift": "2026-06-02",
  "previous_confidence": 0.66,
  "prior_regime": "Risk-on growth",
  "regime_changed_this_run": true,
  "report_date": "2026-06-02",
  "report_transfer": {
    "max_lines": 2,
    "show_in_report": true,
    "summary": "Risk-on narrow leadership has persisted for 1 run(s); transition state is transition_candidate, breadth is mixed, and cross-asset confirmation is mixed."
  },
  "transition_state": "transition_candidate",
  "updated_at_utc": "2026-06-03T15:18:41.831016Z",
  "weeks_in_regime": 1
}