{
  "source": "yfinance",
  "is_live_refresh": true,
  "fallback_used": false,
  "fetched_at_utc": "2026-06-18T18:46:37.789657+00:00",
  "period": "6mo",
  "config": "config/etf_discovery_universe.yml",
  "macro_context": "config/etf_macro_fundamental_context.yml",
  "replacement_target_map_tickers": [
    "BIL",
    "BOTZ",
    "DBC",
    "DFEN",
    "EFA",
    "GLD",
    "GRID",
    "GSG",
    "IEFA",
    "IRBO",
    "ITA",
    "IWM",
    "NATO",
    "NLR",
    "NUCL",
    "PAVE",
    "PPA",
    "QUAL",
    "ROBO",
    "SMH",
    "SOXX",
    "SPY",
    "URA",
    "URNM",
    "VPU",
    "XLU"
  ],
  "tickers_requested": [
    "ARKF",
    "BIL",
    "BOTZ",
    "BUG",
    "CGW",
    "CIBR",
    "COPX",
    "CORN",
    "DBA",
    "DBC",
    "DFEN",
    "EFA",
    "EPI",
    "FINX",
    "FIW",
    "FXI",
    "GLD",
    "GRID",
    "GSG",
    "IAI",
    "IBB",
    "IEFA",
    "INDA",
    "IRBO",
    "ITA",
    "IWM",
    "KCE",
    "KWEB",
    "MCHI",
    "MOO",
    "NATO",
    "NLR",
    "NUCL",
    "PAVE",
    "PHO",
    "PICK",
    "PPA",
    "QUAL",
    "REMX",
    "ROBO",
    "SMH",
    "SOXX",
    "SPY",
    "URA",
    "URNM",
    "VEGI",
    "VHT",
    "VPU",
    "XBI",
    "XLU",
    "XLV"
  ],
  "tickers_returned": [
    "ARKF",
    "BIL",
    "BOTZ",
    "BUG",
    "CGW",
    "CIBR",
    "COPX",
    "CORN",
    "DBA",
    "DBC",
    "DFEN",
    "EFA",
    "EPI",
    "FINX",
    "FIW",
    "FXI",
    "GLD",
    "GRID",
    "GSG",
    "IAI",
    "IBB",
    "IEFA",
    "INDA",
    "IRBO",
    "ITA",
    "IWM",
    "KCE",
    "KWEB",
    "MCHI",
    "MOO",
    "NATO",
    "NLR",
    "NUCL",
    "PAVE",
    "PHO",
    "PICK",
    "PPA",
    "QUAL",
    "REMX",
    "ROBO",
    "SMH",
    "SOXX",
    "SPY",
    "URA",
    "URNM",
    "VEGI",
    "VHT",
    "VPU",
    "XBI",
    "XLU",
    "XLV"
  ],
  "missing_replacement_target_map_tickers": [],
  "metrics": {
    "ARKF": {
      "last_price": 39.779998779296875,
      "return_1w_pct": 2.24,
      "return_1m_pct": -1.78,
      "return_3m_pct": -1.07,
      "trend_quality": 0.0,
      "max_drawdown_3m_pct": -13.76,
      "volatility_3m_pct": 35.81,
      "rs_vs_spy_1w_pct": 1.04,
      "rs_vs_spy_1m_pct": -3.54,
      "rs_vs_spy_3m_pct": -14.54,
      "avg_volume_3m": 183576.98,
      "avg_dollar_volume_3m": 7302692.04,
      "liquidity_score": 3.0,
      "tradability_status": "pass"
    },
    "BIL": {
      "last_price": 91.56500244140625,
      "return_1w_pct": 0.09,
      "return_1m_pct": 0.31,
      "return_3m_pct": 0.91,
      "trend_quality": 5.0,
      "max_drawdown_3m_pct": -0.01,
      "volatility_3m_pct": 0.19,
      "rs_vs_spy_1w_pct": -1.11,
      "rs_vs_spy_1m_pct": -1.45,
      "rs_vs_spy_3m_pct": -12.56,
      "avg_volume_3m": 11668240.87,
      "avg_dollar_volume_3m": 1068402503.75,
      "liquidity_score": 5.0,
      "tradability_status": "pass"
    },
    "BOTZ": {
      "last_price": 38.33399963378906,
      "return_1w_pct": 2.88,
      "return_1m_pct": -1.43,
      "return_3m_pct": 9.9,
      "trend_quality": 1.5,
      "max_drawdown_3m_pct": -12.95,
      "volatility_3m_pct": 32.74,
      "rs_vs_spy_1w_pct": 1.68,
      "rs_vs_spy_1m_pct": -3.19,
      "rs_vs_spy_3m_pct": -3.57,
      "avg_volume_3m": 979852.57,
      "avg_dollar_volume_3m": 37561668.06,
      "liquidity_score": 4.0,
      "tradability_status": "pass"
    },
    "BUG": {
      "last_price": 33.86000061035156,
      "return_1w_pct": -0.85,
      "return_1m_pct": 3.39,
      "return_3m_pct": 28.89,
      "trend_quality": 3.5,
      "max_drawdown_3m_pct": -12.87,
      "volatility_3m_pct": 43.24,
      "rs_vs_spy_1w_pct": -2.05,
      "rs_vs_spy_1m_pct": 1.63,
      "rs_vs_spy_3m_pct": 15.42,
      "avg_volume_3m": 1142898.65,
      "avg_dollar_volume_3m": 38698548.99,
      "liquidity_score": 4.0,
      "tradability_status": "pass"
    },
    "CGW": {
      "last_price": 63.38999938964844,
      "return_1w_pct": 1.47,
      "return_1m_pct": 3.27,
      "return_3m_pct": 0.89,
      "trend_quality": 1.5,
      "max_drawdown_3m_pct": -8.86,
      "volatility_3m_pct": 16.8,
      "rs_vs_spy_1w_pct": 0.27,
      "rs_vs_spy_1m_pct": 1.51,
      "rs_vs_spy_3m_pct": -12.58,
      "avg_volume_3m": 33379.81,
      "avg_dollar_volume_3m": 2115946.14,
      "liquidity_score": 2.0,
      "tradability_status": "watch"
    },
    "CIBR": {
      "last_price": 84.45490264892578,
      "return_1w_pct": -1.19,
      "return_1m_pct": 5.04,
      "return_3m_pct": 29.7,
      "trend_quality": 3.5,
      "max_drawdown_3m_pct": -11.74,
      "volatility_3m_pct": 35.46,
      "rs_vs_spy_1w_pct": -2.39,
      "rs_vs_spy_1m_pct": 3.28,
      "rs_vs_spy_3m_pct": 16.23,
      "avg_volume_3m": 1648186.73,
      "avg_dollar_volume_3m": 139197449.83,
      "liquidity_score": 5.0,
      "tradability_status": "pass"
    },
    "COPX": {
      "last_price": 85.95999908447266,
      "return_1w_pct": 3.37,
      "return_1m_pct": 8.3,
      "return_3m_pct": 18.76,
      "trend_quality": 3.5,
      "max_drawdown_3m_pct": -17.31,
      "volatility_3m_pct": 56.91,
      "rs_vs_spy_1w_pct": 2.17,
      "rs_vs_spy_1m_pct": 6.54,
      "rs_vs_spy_3m_pct": 5.29,
      "avg_volume_3m": 4037168.24,
      "avg_dollar_volume_3m": 347034978.21,
      "liquidity_score": 5.0,
      "tradability_status": "pass"
    },
    "CORN": {
      "last_price": 16.954999923706055,
      "return_1w_pct": 1.41,
      "return_1m_pct": -9.53,
      "return_3m_pct": -9.96,
      "trend_quality": 0.0,
      "max_drawdown_3m_pct": -12.55,
      "volatility_3m_pct": 17.5,
      "rs_vs_spy_1w_pct": 0.21,
      "rs_vs_spy_1m_pct": -11.29,
      "rs_vs_spy_3m_pct": -23.43,
      "avg_volume_3m": 883504.73,
      "avg_dollar_volume_3m": 14979822.63,
      "liquidity_score": 3.0,
      "tradability_status": "pass"
    },
    "DBA": {
      "last_price": 26.635000228881836,
      "return_1w_pct": 1.27,
      "return_1m_pct": -5.82,
      "return_3m_pct": -1.24,
      "trend_quality": 0.0,
      "max_drawdown_3m_pct": -8.67,
      "volatility_3m_pct": 11.27,
      "rs_vs_spy_1w_pct": 0.07,
      "rs_vs_spy_1m_pct": -7.58,
      "rs_vs_spy_3m_pct": -14.71,
      "avg_volume_3m": 1629785.59,
      "avg_dollar_volume_3m": 43409339.56,
      "liquidity_score": 4.0,
      "tradability_status": "pass"
    },
    "DBC": {
      "last_price": 27.649999618530273,
      "return_1w_pct": -4.16,
      "return_1m_pct": -12.53,
      "return_3m_pct": -4.13,
      "trend_quality": 0.0,
      "max_drawdown_3m_pct": -12.75,
      "volatility_3m_pct": 22.75,
      "rs_vs_spy_1w_pct": -5.36,
      "rs_vs_spy_1m_pct": -14.29,
      "rs_vs_spy_3m_pct": -17.6,
      "avg_volume_3m": 1573293.87,
      "avg_dollar_volume_3m": 43501574.91,
      "liquidity_score": 4.0,
      "tradability_status": "pass"
    },
    "DFEN": {
      "last_price": 76.62999725341797,
      "return_1w_pct": 3.23,
      "return_1m_pct": 27.87,
      "return_3m_pct": 6.25,
      "trend_quality": 5.0,
      "max_drawdown_3m_pct": -26.98,
      "volatility_3m_pct": 88.03,
      "rs_vs_spy_1w_pct": 2.03,
      "rs_vs_spy_1m_pct": 26.11,
      "rs_vs_spy_3m_pct": -7.22,
      "avg_volume_3m": 265607.76,
      "avg_dollar_volume_3m": 20353521.92,
      "liquidity_score": 4.0,
      "tradability_status": "pass"
    },
    "EFA": {
      "last_price": 104.42500305175781,
      "return_1w_pct": 1.29,
      "return_1m_pct": 4.08,
      "return_3m_pct": 9.9,
      "trend_quality": 5.0,
      "max_drawdown_3m_pct": -4.21,
      "volatility_3m_pct": 21.36,
      "rs_vs_spy_1w_pct": 0.09,
      "rs_vs_spy_1m_pct": 2.32,
      "rs_vs_spy_3m_pct": -3.57,
      "avg_volume_3m": 16522895.16,
      "avg_dollar_volume_3m": 1725403377.51,
      "liquidity_score": 5.0,
      "tradability_status": "pass"
    },
    "EPI": {
      "last_price": 43.04999923706055,
      "return_1w_pct": 2.99,
      "return_1m_pct": 3.99,
      "return_3m_pct": 4.29,
      "trend_quality": 2.5,
      "max_drawdown_3m_pct": -7.89,
      "volatility_3m_pct": 20.51,
      "rs_vs_spy_1w_pct": 1.79,
      "rs_vs_spy_1m_pct": 2.23,
      "rs_vs_spy_3m_pct": -9.18,
      "avg_volume_3m": 714200.08,
      "avg_dollar_volume_3m": 30746312.9,
      "liquidity_score": 4.0,
      "tradability_status": "pass"
    },
    "FINX": {
      "last_price": 24.84000015258789,
      "return_1w_pct": 3.28,
      "return_1m_pct": 0.38,
      "return_3m_pct": 2.35,
      "trend_quality": 1.5,
      "max_drawdown_3m_pct": -13.05,
      "volatility_3m_pct": 34.08,
      "rs_vs_spy_1w_pct": 2.08,
      "rs_vs_spy_1m_pct": -1.38,
      "rs_vs_spy_3m_pct": -11.12,
      "avg_volume_3m": 69965.98,
      "avg_dollar_volume_3m": 1737954.95,
      "liquidity_score": 2.0,
      "tradability_status": "watch"
    },
    "FIW": {
      "last_price": 106.15499877929688,
      "return_1w_pct": 1.37,
      "return_1m_pct": 6.52,
      "return_3m_pct": 3.1,
      "trend_quality": 2.5,
      "max_drawdown_3m_pct": -8.49,
      "volatility_3m_pct": 17.78,
      "rs_vs_spy_1w_pct": 0.17,
      "rs_vs_spy_1m_pct": 4.76,
      "rs_vs_spy_3m_pct": -10.37,
      "avg_volume_3m": 62234.06,
      "avg_dollar_volume_3m": 6606456.56,
      "liquidity_score": 3.0,
      "tradability_status": "pass"
    },
    "FXI": {
      "last_price": 33.28499984741211,
      "return_1w_pct": -3.94,
      "return_1m_pct": -7.57,
      "return_3m_pct": -7.34,
      "trend_quality": 0.0,
      "max_drawdown_3m_pct": -12.35,
      "volatility_3m_pct": 21.26,
      "rs_vs_spy_1w_pct": -5.14,
      "rs_vs_spy_1m_pct": -9.33,
      "rs_vs_spy_3m_pct": -20.81,
      "avg_volume_3m": 29145538.17,
      "avg_dollar_volume_3m": 970109233.54,
      "liquidity_score": 5.0,
      "tradability_status": "pass"
    },
    "GLD": {
      "last_price": 387.70001220703125,
      "return_1w_pct": 0.36,
      "return_1m_pct": -5.78,
      "return_3m_pct": -9.08,
      "trend_quality": 0.0,
      "max_drawdown_3m_pct": -16.0,
      "volatility_3m_pct": 27.65,
      "rs_vs_spy_1w_pct": -0.84,
      "rs_vs_spy_1m_pct": -7.54,
      "rs_vs_spy_3m_pct": -22.55,
      "avg_volume_3m": 8776638.71,
      "avg_dollar_volume_3m": 3402702935.0,
      "liquidity_score": 5.0,
      "tradability_status": "pass"
    },
    "GRID": {
      "last_price": 194.6999969482422,
      "return_1w_pct": 2.82,
      "return_1m_pct": 5.24,
      "return_3m_pct": 17.11,
      "trend_quality": 5.0,
      "max_drawdown_3m_pct": -9.16,
      "volatility_3m_pct": 30.4,
      "rs_vs_spy_1w_pct": 1.62,
      "rs_vs_spy_1m_pct": 3.48,
      "rs_vs_spy_3m_pct": 3.64,
      "avg_volume_3m": 783108.52,
      "avg_dollar_volume_3m": 152471226.45,
      "liquidity_score": 5.0,
      "tradability_status": "pass"
    },
    "GSG": {
      "last_price": 29.5049991607666,
      "return_1w_pct": -4.7,
      "return_1m_pct": -15.14,
      "return_3m_pct": -5.73,
      "trend_quality": 0.0,
      "max_drawdown_3m_pct": -15.27,
      "volatility_3m_pct": 32.64,
      "rs_vs_spy_1w_pct": -5.9,
      "rs_vs_spy_1m_pct": -16.9,
      "rs_vs_spy_3m_pct": -19.2,
      "avg_volume_3m": 1286392.81,
      "avg_dollar_volume_3m": 37955018.78,
      "liquidity_score": 4.0,
      "tradability_status": "pass"
    },
    "IAI": {
      "last_price": 185.94000244140625,
      "return_1w_pct": 3.02,
      "return_1m_pct": 5.85,
      "return_3m_pct": 13.94,
      "trend_quality": 5.0,
      "max_drawdown_3m_pct": -4.45,
      "volatility_3m_pct": 19.11,
      "rs_vs_spy_1w_pct": 1.82,
      "rs_vs_spy_1m_pct": 4.09,
      "rs_vs_spy_3m_pct": 0.47,
      "avg_volume_3m": 114595.98,
      "avg_dollar_volume_3m": 21307976.8,
      "liquidity_score": 4.0,
      "tradability_status": "pass"
    },
    "IBB": {
      "last_price": 173.22999572753906,
      "return_1w_pct": 1.62,
      "return_1m_pct": 5.52,
      "return_3m_pct": 5.35,
      "trend_quality": 3.5,
      "max_drawdown_3m_pct": -7.15,
      "volatility_3m_pct": 23.98,
      "rs_vs_spy_1w_pct": 0.42,
      "rs_vs_spy_1m_pct": 3.76,
      "rs_vs_spy_3m_pct": -8.12,
      "avg_volume_3m": 1446418.54,
      "avg_dollar_volume_3m": 250563077.5,
      "liquidity_score": 5.0,
      "tradability_status": "pass"
    },
    "IEFA": {
      "last_price": 97.2750015258789,
      "return_1w_pct": 1.1,
      "return_1m_pct": 3.67,
      "return_3m_pct": 9.8,
      "trend_quality": 5.0,
      "max_drawdown_3m_pct": -4.21,
      "volatility_3m_pct": 21.36,
      "rs_vs_spy_1w_pct": -0.1,
      "rs_vs_spy_1m_pct": 1.91,
      "rs_vs_spy_3m_pct": -3.67,
      "avg_volume_3m": 11097175.35,
      "avg_dollar_volume_3m": 1079477749.1,
      "liquidity_score": 5.0,
      "tradability_status": "pass"
    },
    "INDA": {
      "last_price": 49.60499954223633,
      "return_1w_pct": 3.8,
      "return_1m_pct": 4.94,
      "return_3m_pct": 4.39,
      "trend_quality": 2.5,
      "max_drawdown_3m_pct": -7.94,
      "volatility_3m_pct": 21.11,
      "rs_vs_spy_1w_pct": 2.6,
      "rs_vs_spy_1m_pct": 3.18,
      "rs_vs_spy_3m_pct": -9.08,
      "avg_volume_3m": 7631882.13,
      "avg_dollar_volume_3m": 378579509.57,
      "liquidity_score": 5.0,
      "tradability_status": "pass"
    },
    "IRBO": {
      "last_price": 73.22659301757812,
      "return_1w_pct": 1.08,
      "return_1m_pct": 14.86,
      "return_3m_pct": 46.16,
      "trend_quality": 3.5,
      "max_drawdown_3m_pct": -15.07,
      "volatility_3m_pct": 47.0,
      "rs_vs_spy_1w_pct": -0.12,
      "rs_vs_spy_1m_pct": 13.1,
      "rs_vs_spy_3m_pct": 32.69,
      "avg_volume_3m": 836581.86,
      "avg_dollar_volume_3m": 61260039.39,
      "liquidity_score": 5.0,
      "tradability_status": "pass"
    },
    "ITA": {
      "last_price": 238.78750610351562,
      "return_1w_pct": 1.24,
      "return_1m_pct": 9.45,
      "return_3m_pct": 5.12,
      "trend_quality": 5.0,
      "max_drawdown_3m_pct": -9.47,
      "volatility_3m_pct": 28.86,
      "rs_vs_spy_1w_pct": 0.04,
      "rs_vs_spy_1m_pct": 7.69,
      "rs_vs_spy_3m_pct": -8.35,
      "avg_volume_3m": 916663.73,
      "avg_dollar_volume_3m": 218887846.02,
      "liquidity_score": 5.0,
      "tradability_status": "pass"
    },
    "IWM": {
      "last_price": 294.69000244140625,
      "return_1w_pct": 1.72,
      "return_1m_pct": 8.2,
      "return_3m_pct": 19.29,
      "trend_quality": 5.0,
      "max_drawdown_3m_pct": -4.85,
      "volatility_3m_pct": 21.89,
      "rs_vs_spy_1w_pct": 0.52,
      "rs_vs_spy_1m_pct": 6.44,
      "rs_vs_spy_3m_pct": 5.82,
      "avg_volume_3m": 32018415.76,
      "avg_dollar_volume_3m": 9435507018.48,
      "liquidity_score": 5.0,
      "tradability_status": "pass"
    },
    "KCE": {
      "last_price": 154.1750030517578,
      "return_1w_pct": 1.32,
      "return_1m_pct": 3.05,
      "return_3m_pct": 13.33,
      "trend_quality": 5.0,
      "max_drawdown_3m_pct": -4.27,
      "volatility_3m_pct": 19.34,
      "rs_vs_spy_1w_pct": 0.12,
      "rs_vs_spy_1m_pct": 1.29,
      "rs_vs_spy_3m_pct": -0.14,
      "avg_volume_3m": 15681.37,
      "avg_dollar_volume_3m": 2417675.27,
      "liquidity_score": 2.0,
      "tradability_status": "watch"
    },
    "KWEB": {
      "last_price": 25.225000381469727,
      "return_1w_pct": -5.06,
      "return_1m_pct": -10.8,
      "return_3m_pct": -13.29,
      "trend_quality": 0.0,
      "max_drawdown_3m_pct": -17.54,
      "volatility_3m_pct": 31.15,
      "rs_vs_spy_1w_pct": -6.26,
      "rs_vs_spy_1m_pct": -12.56,
      "rs_vs_spy_3m_pct": -26.76,
      "avg_volume_3m": 25901173.4,
      "avg_dollar_volume_3m": 653357108.9,
      "liquidity_score": 5.0,
      "tradability_status": "pass"
    },
    "MCHI": {
      "last_price": 52.74129867553711,
      "return_1w_pct": -2.3,
      "return_1m_pct": -6.17,
      "return_3m_pct": -6.55,
      "trend_quality": 0.0,
      "max_drawdown_3m_pct": -11.2,
      "volatility_3m_pct": 21.69,
      "rs_vs_spy_1w_pct": -3.5,
      "rs_vs_spy_1m_pct": -7.93,
      "rs_vs_spy_3m_pct": -20.02,
      "avg_volume_3m": 3098921.6,
      "avg_dollar_volume_3m": 163441149.68,
      "liquidity_score": 5.0,
      "tradability_status": "pass"
    },
    "MOO": {
      "last_price": 76.94020080566406,
      "return_1w_pct": -1.27,
      "return_1m_pct": -5.04,
      "return_3m_pct": -6.63,
      "trend_quality": 0.0,
      "max_drawdown_3m_pct": -10.68,
      "volatility_3m_pct": 14.74,
      "rs_vs_spy_1w_pct": -2.47,
      "rs_vs_spy_1m_pct": -6.8,
      "rs_vs_spy_3m_pct": -20.1,
      "avg_volume_3m": 379771.78,
      "avg_dollar_volume_3m": 29219717.01,
      "liquidity_score": 4.0,
      "tradability_status": "pass"
    },
    "NATO": {
      "last_price": 40.348899841308594,
      "return_1w_pct": 0.45,
      "return_1m_pct": 6.15,
      "return_3m_pct": -0.07,
      "trend_quality": 5.0,
      "max_drawdown_3m_pct": -9.95,
      "volatility_3m_pct": 30.33,
      "rs_vs_spy_1w_pct": -0.75,
      "rs_vs_spy_1m_pct": 4.39,
      "rs_vs_spy_3m_pct": -13.54,
      "avg_volume_3m": 34673.25,
      "avg_dollar_volume_3m": 1399027.49,
      "liquidity_score": 2.0,
      "tradability_status": "watch"
    },
    "NLR": {
      "last_price": 126.16000366210938,
      "return_1w_pct": 4.32,
      "return_1m_pct": 0.88,
      "return_3m_pct": -5.58,
      "trend_quality": 0.0,
      "max_drawdown_3m_pct": -22.6,
      "volatility_3m_pct": 46.43,
      "rs_vs_spy_1w_pct": 3.12,
      "rs_vs_spy_1m_pct": -0.88,
      "rs_vs_spy_3m_pct": -19.05,
      "avg_volume_3m": 476759.56,
      "avg_dollar_volume_3m": 60147987.84,
      "liquidity_score": 5.0,
      "tradability_status": "pass"
    },
    "NUCL": {
      "last_price": 10.074999809265137,
      "return_1w_pct": 7.18,
      "return_1m_pct": -6.28,
      "return_3m_pct": 94.5,
      "trend_quality": 1.5,
      "max_drawdown_3m_pct": -30.89,
      "volatility_3m_pct": 137.41,
      "rs_vs_spy_1w_pct": 5.98,
      "rs_vs_spy_1m_pct": -8.04,
      "rs_vs_spy_3m_pct": 81.03,
      "avg_volume_3m": 452416.62,
      "avg_dollar_volume_3m": 4558097.36,
      "liquidity_score": 2.0,
      "tradability_status": "watch"
    },
    "PAVE": {
      "last_price": 58.61000061035156,
      "return_1w_pct": 2.5,
      "return_1m_pct": 9.0,
      "return_3m_pct": 17.24,
      "trend_quality": 5.0,
      "max_drawdown_3m_pct": -7.85,
      "volatility_3m_pct": 24.68,
      "rs_vs_spy_1w_pct": 1.3,
      "rs_vs_spy_1m_pct": 7.24,
      "rs_vs_spy_3m_pct": 3.77,
      "avg_volume_3m": 1645552.38,
      "avg_dollar_volume_3m": 96445826.0,
      "liquidity_score": 5.0,
      "tradability_status": "pass"
    },
    "PHO": {
      "last_price": 67.58000183105469,
      "return_1w_pct": 1.79,
      "return_1m_pct": 5.35,
      "return_3m_pct": 1.74,
      "trend_quality": 2.5,
      "max_drawdown_3m_pct": -9.01,
      "volatility_3m_pct": 16.28,
      "rs_vs_spy_1w_pct": 0.59,
      "rs_vs_spy_1m_pct": 3.59,
      "rs_vs_spy_3m_pct": -11.73,
      "avg_volume_3m": 120838.7,
      "avg_dollar_volume_3m": 8166279.57,
      "liquidity_score": 3.0,
      "tradability_status": "pass"
    },
    "PICK": {
      "last_price": 63.13999938964844,
      "return_1w_pct": -0.17,
      "return_1m_pct": 4.43,
      "return_3m_pct": 18.35,
      "trend_quality": 3.5,
      "max_drawdown_3m_pct": -12.46,
      "volatility_3m_pct": 38.94,
      "rs_vs_spy_1w_pct": -1.37,
      "rs_vs_spy_1m_pct": 2.67,
      "rs_vs_spy_3m_pct": 4.88,
      "avg_volume_3m": 683105.73,
      "avg_dollar_volume_3m": 43131295.38,
      "liquidity_score": 4.0,
      "tradability_status": "pass"
    },
    "PPA": {
      "last_price": 174.61500549316406,
      "return_1w_pct": -0.97,
      "return_1m_pct": 5.8,
      "return_3m_pct": 1.08,
      "trend_quality": 5.0,
      "max_drawdown_3m_pct": -7.95,
      "volatility_3m_pct": 26.36,
      "rs_vs_spy_1w_pct": -2.17,
      "rs_vs_spy_1m_pct": 4.04,
      "rs_vs_spy_3m_pct": -12.39,
      "avg_volume_3m": 251746.43,
      "avg_dollar_volume_3m": 43958704.26,
      "liquidity_score": 4.0,
      "tradability_status": "pass"
    },
    "QUAL": {
      "last_price": 216.0500030517578,
      "return_1w_pct": 0.25,
      "return_1m_pct": 3.28,
      "return_3m_pct": 11.44,
      "trend_quality": 5.0,
      "max_drawdown_3m_pct": -3.93,
      "volatility_3m_pct": 14.56,
      "rs_vs_spy_1w_pct": -0.95,
      "rs_vs_spy_1m_pct": 1.52,
      "rs_vs_spy_3m_pct": -2.03,
      "avg_volume_3m": 1901339.76,
      "avg_dollar_volume_3m": 410784460.95,
      "liquidity_score": 5.0,
      "tradability_status": "pass"
    },
    "REMX": {
      "last_price": 95.45999908447266,
      "return_1w_pct": 2.69,
      "return_1m_pct": 3.61,
      "return_3m_pct": 15.08,
      "trend_quality": 0.0,
      "max_drawdown_3m_pct": -22.28,
      "volatility_3m_pct": 51.88,
      "rs_vs_spy_1w_pct": 1.49,
      "rs_vs_spy_1m_pct": 1.85,
      "rs_vs_spy_3m_pct": 1.61,
      "avg_volume_3m": 1070764.17,
      "avg_dollar_volume_3m": 102215146.69,
      "liquidity_score": 5.0,
      "tradability_status": "pass"
    },
    "ROBO": {
      "last_price": 85.76499938964844,
      "return_1w_pct": 4.05,
      "return_1m_pct": 3.94,
      "return_3m_pct": 21.38,
      "trend_quality": 3.5,
      "max_drawdown_3m_pct": -12.0,
      "volatility_3m_pct": 34.33,
      "rs_vs_spy_1w_pct": 2.85,
      "rs_vs_spy_1m_pct": 2.18,
      "rs_vs_spy_3m_pct": 7.91,
      "avg_volume_3m": 214156.48,
      "avg_dollar_volume_3m": 18367130.38,
      "liquidity_score": 3.0,
      "tradability_status": "pass"
    },
    "SMH": {
      "last_price": 659.25,
      "return_1w_pct": 8.17,
      "return_1m_pct": 21.19,
      "return_3m_pct": 66.93,
      "trend_quality": 5.0,
      "max_drawdown_3m_pct": -10.69,
      "volatility_3m_pct": 46.87,
      "rs_vs_spy_1w_pct": 6.97,
      "rs_vs_spy_1m_pct": 19.43,
      "rs_vs_spy_3m_pct": 53.46,
      "avg_volume_3m": 10013481.59,
      "avg_dollar_volume_3m": 6601387738.21,
      "liquidity_score": 5.0,
      "tradability_status": "pass"
    },
    "SOXX": {
      "last_price": 638.47998046875,
      "return_1w_pct": 8.83,
      "return_1m_pct": 28.6,
      "return_3m_pct": 87.77,
      "trend_quality": 5.0,
      "max_drawdown_3m_pct": -12.33,
      "volatility_3m_pct": 54.86,
      "rs_vs_spy_1w_pct": 7.63,
      "rs_vs_spy_1m_pct": 26.84,
      "rs_vs_spy_3m_pct": 74.3,
      "avg_volume_3m": 8644824.03,
      "avg_dollar_volume_3m": 5519547077.83,
      "liquidity_score": 5.0,
      "tradability_status": "pass"
    },
    "SPY": {
      "last_price": 746.6199951171875,
      "return_1w_pct": 1.2,
      "return_1m_pct": 1.76,
      "return_3m_pct": 13.47,
      "trend_quality": 3.5,
      "max_drawdown_3m_pct": -4.49,
      "volatility_3m_pct": 15.43,
      "rs_vs_spy_1w_pct": 0.0,
      "rs_vs_spy_1m_pct": 0.0,
      "rs_vs_spy_3m_pct": 0.0,
      "avg_volume_3m": 62802068.35,
      "avg_dollar_volume_3m": 46889279964.83,
      "liquidity_score": 5.0,
      "tradability_status": "pass"
    },
    "URA": {
      "last_price": 47.59000015258789,
      "return_1w_pct": 6.16,
      "return_1m_pct": 0.83,
      "return_3m_pct": -1.41,
      "trend_quality": 0.0,
      "max_drawdown_3m_pct": -27.31,
      "volatility_3m_pct": 57.04,
      "rs_vs_spy_1w_pct": 4.96,
      "rs_vs_spy_1m_pct": -0.93,
      "rs_vs_spy_3m_pct": -14.88,
      "avg_volume_3m": 3952308.97,
      "avg_dollar_volume_3m": 188090384.49,
      "liquidity_score": 5.0,
      "tradability_status": "pass"
    },
    "URNM": {
      "last_price": 57.290000915527344,
      "return_1w_pct": 5.53,
      "return_1m_pct": 0.37,
      "return_3m_pct": -5.93,
      "trend_quality": 0.0,
      "max_drawdown_3m_pct": -27.87,
      "volatility_3m_pct": 57.02,
      "rs_vs_spy_1w_pct": 4.33,
      "rs_vs_spy_1m_pct": -1.39,
      "rs_vs_spy_3m_pct": -19.4,
      "avg_volume_3m": 720060.33,
      "avg_dollar_volume_3m": 41252256.96,
      "liquidity_score": 4.0,
      "tradability_status": "pass"
    },
    "VEGI": {
      "last_price": 43.064998626708984,
      "return_1w_pct": 0.19,
      "return_1m_pct": -2.47,
      "return_3m_pct": -2.51,
      "trend_quality": 0.0,
      "max_drawdown_3m_pct": -7.95,
      "volatility_3m_pct": 15.88,
      "rs_vs_spy_1w_pct": -1.01,
      "rs_vs_spy_1m_pct": -4.23,
      "rs_vs_spy_3m_pct": -15.98,
      "avg_volume_3m": 85285.68,
      "avg_dollar_volume_3m": 3672827.69,
      "liquidity_score": 2.0,
      "tradability_status": "watch"
    },
    "VHT": {
      "last_price": 280.760009765625,
      "return_1w_pct": -2.11,
      "return_1m_pct": 2.45,
      "return_3m_pct": 3.64,
      "trend_quality": 3.5,
      "max_drawdown_3m_pct": -4.18,
      "volatility_3m_pct": 15.85,
      "rs_vs_spy_1w_pct": -3.31,
      "rs_vs_spy_1m_pct": 0.69,
      "rs_vs_spy_3m_pct": -9.83,
      "avg_volume_3m": 210250.1,
      "avg_dollar_volume_3m": 59029820.13,
      "liquidity_score": 5.0,
      "tradability_status": "pass"
    },
    "VPU": {
      "last_price": 193.8800048828125,
      "return_1w_pct": 1.67,
      "return_1m_pct": 0.95,
      "return_3m_pct": -2.79,
      "trend_quality": 1.5,
      "max_drawdown_3m_pct": -8.11,
      "volatility_3m_pct": 18.24,
      "rs_vs_spy_1w_pct": 0.47,
      "rs_vs_spy_1m_pct": -0.81,
      "rs_vs_spy_3m_pct": -16.26,
      "avg_volume_3m": 239306.29,
      "avg_dollar_volume_3m": 46396704.67,
      "liquidity_score": 4.0,
      "tradability_status": "pass"
    },
    "XBI": {
      "last_price": 140.24000549316406,
      "return_1w_pct": 5.65,
      "return_1m_pct": 10.61,
      "return_3m_pct": 14.64,
      "trend_quality": 3.5,
      "max_drawdown_3m_pct": -8.57,
      "volatility_3m_pct": 32.93,
      "rs_vs_spy_1w_pct": 4.45,
      "rs_vs_spy_1m_pct": 8.85,
      "rs_vs_spy_3m_pct": 1.17,
      "avg_volume_3m": 8905404.84,
      "avg_dollar_volume_3m": 1248894023.68,
      "liquidity_score": 5.0,
      "tradability_status": "pass"
    },
    "XLU": {
      "last_price": 44.75,
      "return_1w_pct": 1.59,
      "return_1m_pct": 0.92,
      "return_3m_pct": -3.17,
      "trend_quality": 1.5,
      "max_drawdown_3m_pct": -8.59,
      "volatility_3m_pct": 18.44,
      "rs_vs_spy_1w_pct": 0.39,
      "rs_vs_spy_1m_pct": -0.84,
      "rs_vs_spy_3m_pct": -16.64,
      "avg_volume_3m": 21661689.67,
      "avg_dollar_volume_3m": 969360612.73,
      "liquidity_score": 5.0,
      "tradability_status": "pass"
    },
    "XLV": {
      "last_price": 149.78500366210938,
      "return_1w_pct": -2.79,
      "return_1m_pct": 1.67,
      "return_3m_pct": 2.59,
      "trend_quality": 3.5,
      "max_drawdown_3m_pct": -4.56,
      "volatility_3m_pct": 15.94,
      "rs_vs_spy_1w_pct": -3.99,
      "rs_vs_spy_1m_pct": -0.09,
      "rs_vs_spy_3m_pct": -10.88,
      "avg_volume_3m": 10734431.43,
      "avg_dollar_volume_3m": 1607856851.05,
      "liquidity_score": 5.0,
      "tradability_status": "pass"
    }
  }
}